{"basics":{"name":"Ryan Crowe","label":"Entry-Level Game Developer","image":"","email":"ryan.n.crowe@gmail.com","phone":"(+61) 434 272 998","summary":"Final term university student with an interest in dynamic systems and graphics programming","location":{"city":"Sydney","region":"Australia"}},"work":[{"name":"China Legend Restaurant","position":"Delivery Driver, Part-time","startDate":"2023","endDate":"2024"},{"name":"Datacom NSW","position":"Customer Service Representative","startDate":"2018-04","endDate":"2019-01","summary":"External call centre for ATO (Australian Taxation Office) taking individual, business and debt tax enquiries."}],"education":[{"institution":"Macquarie University","location":"Sydney, Australia","url":"https://www.mq.edu.au/","area":"Software Technology","studyType":"Bachelor of IT","startDate":"2022","endDate":"2025-10"},{"institution":"Production Art Department","location":"Sydney, Australia","url":"https://productionartdepartment.com/","area":"Illustration and Concept Art","studyType":"Independent/Vocational Training","startDate":"2017-01","endDate":"2017-12"}],"skills":[{"name":"Programming","icon":"fa-solid fa-hashtag","keywords":["C#","Java","C","GLSL","HLSL"]},{"name":"Game Engines","icon":"fa-solid fa-hashtag","keywords":["Unity"]},{"name":"Version Control","icon":"fa-solid fa-hashtag","keywords":["Git","Github"]}],"projects":[{"name":"VULTUR","summary":"Atmospheric Biopunk Mech-Shooter","position":"Lead Programmer & Art Direction","highlights":["SXSW 2024 Student Showcase","Dynamic Upgrade System"],"startDate":"2024-02","endDate":"2024-10","url":"https://oberindraco.itch.io/project-vulture-alpha-build"},{"name":"Terminal Velocity","summary":"Physics-based, gravity defying, Dodgeball in space","position":"Programmer & Shader Programmer","startDate":"2024-05","endDate":"2024-07","highlights":["Macquarie University Astronomy Open Night Games Showcase 2024","Local multiplayer up to 8 players"],"url":"https://harley-james.itch.io/terminalvelocity"}]}